global_service_fastapi_pkg/__init__.py
global_service_fastapi_pkg/admin_utils.py
global_service_fastapi_pkg/app_version.py
global_service_fastapi_pkg/debug_log_flag_manager.py
global_service_fastapi_pkg/get_flush_interval.py
global_service_fastapi_pkg/global_service_fastapi_pkg.py
global_service_fastapi_pkg/global_service_fastapi_pkg1.py
global_service_fastapi_pkg/ip_utils.py
global_service_fastapi_pkg/oracle_date_formatter.py
lhs_global_service_fastapi-0.2.5.dist-info/licenses/LICENSE
lhs_global_service_fastapi-0.2.5.dist-info/METADATA
lhs_global_service_fastapi-0.2.5.dist-info/WHEEL
lhs_global_service_fastapi-0.2.5.dist-info/top_level.txt
lhs_global_service_fastapi-0.2.5.dist-info/RECORD
