Metadata-Version: 2.4
Name: lhs-global-service-fastapi
Version: 0.2.5
Summary: Global Oracle logging and debug management for FastAPI apps.
Home-page: https://github.com/yourusername/your-repo
Author: Rohit Jagtap
Author-email: rohit.jagtap@lighthouseindia.com
License: MIT
Project-URL: Source, https://github.com/yourusername/your-repo
Project-URL: Tracker, https://github.com/yourusername/your-repo/issues
Keywords: oracle,logging,fastapi,debug,global-service
Classifier: Programming Language :: Python :: 3
Classifier: License :: OSI Approved :: MIT License
Classifier: Operating System :: OS Independent
Requires-Python: >=3.9
License-File: LICENSE
Requires-Dist: cx_Oracle
Requires-Dist: requests
Requires-Dist: python-dotenv
Dynamic: author
Dynamic: author-email
Dynamic: classifier
Dynamic: description
Dynamic: description-content-type
Dynamic: home-page
Dynamic: keywords
Dynamic: license
Dynamic: license-file
Dynamic: project-url
Dynamic: requires-dist
Dynamic: requires-python
Dynamic: summary
